genieapi/Error.py
genieapi/GenieAPI.py
genieapi/__init__.py
genieapi-0.1.3.dist-info/METADATA
genieapi-0.1.3.dist-info/WHEEL
genieapi-0.1.3.dist-info/top_level.txt
genieapi-0.1.3.dist-info/RECORD
